odoo9_addon_web_notify-9.0.1.1.0-py2.7-nspkg.pth
odoo9_addon_web_notify-9.0.1.1.0.dist-info/METADATA
odoo9_addon_web_notify-9.0.1.1.0.dist-info/RECORD
odoo9_addon_web_notify-9.0.1.1.0.dist-info/WHEEL
odoo9_addon_web_notify-9.0.1.1.0.dist-info/namespace_packages.txt
odoo9_addon_web_notify-9.0.1.1.0.dist-info/top_level.txt
odoo_addons/web_notify/README.rst
odoo_addons/web_notify/__init__.py
odoo_addons/web_notify/__openerp__.py
odoo_addons/web_notify/i18n/ca.po
odoo_addons/web_notify/i18n/de.po
odoo_addons/web_notify/i18n/es.po
odoo_addons/web_notify/i18n/fr.po
odoo_addons/web_notify/i18n/pt_BR.po
odoo_addons/web_notify/models/__init__.py
odoo_addons/web_notify/models/res_users.py
odoo_addons/web_notify/static/description/icon.png
odoo_addons/web_notify/static/description/notifications_screenshot.png
odoo_addons/web_notify/static/src/js/web_client.js
odoo_addons/web_notify/tests/__init__.py
odoo_addons/web_notify/tests/test_res_users.py
odoo_addons/web_notify/views/web_notify.xml
